{"Genocide in the Ottoman Empire : Armenians, Assyrians, and Greeks, 1913-1923": [["George Shirinian", "New York : Berghahn Books, 2017.", "1785334328 / 9781785334320"]], "The Russian revolution, 1905-1921": [["Mark D. Steinberg", "Oxford : Oxford University Press, 2017.", "0199227624 / 9780199227624"]], "From craftsmen to capitalists : German artisans from the Third Reich to the Federal Republic, 1939-1953": [["Frederick L. McKitrick", "New York : Berghahn, 2016.", "1785332481 / 9781785332487"]], "Making history matter : Kuroita Katsumi and the construction of Imperial Japan": [["Lisa Yoshikawa", "Cambridge, Massachusetts : Harvard University Asia Center, 2017.", "0674975170 / 9780674975170"]], "Global scientific practice in an age of revolutions, 1750-1850": [["Patrick Manning", "Pittsburgh, Pa. : University of Pittsburgh Press, [2016?].", "0822944545 / 9780822944546"]], "Exploratory experiments : Amp\u00e8re, Faraday, and the origins of electrodynamics": [["Friedrich Steinle", "Pittsburgh : University of Pittsburgh Press, [2016?].", "0822944502 / 9780822944508"]], "Byzantine legal culture and the Roman legal tradition, 867-1056": [["Zachary Chitwood", "Cambridge : Cambridge University Press, 2017.", "1107182565 / 9781107182561"]], "The Red Army and the Second World War": [["Alexander Hill", "Cambridge: Cambridge University Press, 2017.", "1107020794 / 9781107020795"]], "Henry VI": [["James Ross", "London : Allen Lane, 2016.", "0141979348 / 9780141979342"]], "The law of nations in global history": [["Charles Henry Alexandrowicz", "Oxford : Oxford University Press, 2017.", "0198766076 / 9780198766070"]], "Clerical households in late Medieval Italy": [["Roisin Cossar", "Cambridge, Massachusetts : Harvard University Press, 2017.", "0674971892 / 9780674971899"]], "The Old English history of the world : an Anglo-Saxon rewriting of Orosius": [["Paulus Orosius", "Cambridge, Massachusetts : Harvard University Press, 2016.", "067497106X / 9780674971066"]], "Byzantium and the emergence of Muslim-Turkish Anatolia, ca. 1040-1130": [["Alexander Daniel Beihammer", "Abingdon, Oxon ; New York, NY : Routledge, an imprint of the Taylor &amp; Francis Group, 2017.", "1138229598 / 9781138229594"]], "What is environmental history?": [["J. Donald Hughes", "Cambridge : Polity, 2016.", "074568842X / 9780745688428"]], "Rethinking American emancipation : legacies of slavery and the quest for black freedom": [["William A. Link", "New York, NY : Cambridge University Press, 2016.", "1107073030 / 9781107073036"]], "The American century and beyond : U.S. foreign relations, 1893-2015": [["George C. Herring", "New York : Oxford University Press, 2017.", "0190212470 / 9780190212476"]], "The kingdom of Wurttemberg and the making of Germany, 1815-1871": [["Bodie A. Ashton", "London : Bloomsbury Academic, 2017.", "1350000078 / 9781350000070"]], "The shaping of Turkey in the British imagination, 1776-1923": [["David S. Katz", "Cham : Palgrave Macmillan, [2016?]", "3319410598 / 9783319410593"]], "Feminism unfinished : a short, surprising history of American women's movements": [["Dorothy Sue Cobble", "New York ; London : Liveright Publishing Corporation, 2014.", "0871406764 / 9780871406767"]], "Does history make sense? : Hegel on the historical shapes of justice": [["Terry P. Pinkard", "Cambridge, Massachusetts : Harvard University Press, 2017.", "0674971779 / 9780674971776"]], "Arabic thought beyond the liberal age : towards an intellectual history of the Nahda": [["Jens Hanssen", "Cambridge : Cambridge University Press, 2016.", "1107136334 / 9781107136335"]], "The third reign of Louis XIV, c.1682-1715": [["Julia Prest", "London : Routledge, 2017.", "1472475003 / 9781472475008"]], "Alice in Westminster : the political life of Alice Bacon": [["Rachel Reeves", "London : I.B. Tauris, 2017.", "1784537683 / 9781784537685"]], "Ye that are men now serve him : radical holiness theology and gender in the South": [["Colin B. Chapell", "Tuscaloosa : The University of Alabama Press, 2016.", "0817319220 / 9780817319229"]], "New political ideas in the aftermath of the Great War": [["Alessandro Salvador", "Cham : Palgrave Macmillan, [2017]", "3319389149 / 9783319389141"]], "The anarchy : war and status in 12th-century landscapes of conflict": [["O. H. Creighton", "Liverpool : Liverpool University Press, 2016.", "1781382425 / 9781781382424"]], "Adolescent girlhood and literary culture at the fin de siecle : daughters of today": [["Beth Rodgers", "Basingstoke : Palgrave Macmillan, [2016?]", "3319326236 / 9783319326238"]], "Longing for the lost caliphate : a transregional history": [["Mona Hassan", "Princeton, New Jersey : Princeton University Press, [2016?]", "0691166781 / 9780691166780"]], "Proctors for parliament : clergy, community and politics, c. 1248-1539 (The National Archives, Series SC 10). Volume I, C. 1248-1377": [["Phil Bradford", "Woodbridge, Suffolk : The Boydell Press [for] The Canterbury and York Society, 2017.", "0907239803 / 9780907239802"]], "Meetings with remarkable manuscripts": [["Christopher de Hamel", "London : Allen Lane, 2016.", "0241003040 / 9780241003046"]], "The making of England : a new history of the Anglo-Saxon world": [["Mark Atherton", "London : I.B. Tauris, 2017.", "1784530050 / 9781784530051"]], "Anxieties, fear and panic in colonial settings : empires on the verge of a nervous breakdown": [["Harald Fischer-Tin\u00a9\u266d", "Cham, Switzerland : Palgrave Macmillan, [2016?]", "3319451359 / 9783319451350"]], "A savage war : a military history of the Civil War": [["Williamson Murray", "Princeton : Princeton University Press, [2016?].", "0691169403 / 9780691169408"]], "The house of the dead : Siberian exile under the tsars": [["Daniel Beer", "London : Allen Lane, 2016.", "1846145376 / 9781846145377"]], "Informed power : communication in the early American South": [["Alejandra Dubcovsky", "Cambridge, Massachusetts : Harvard University Press, 2016.", "0674660188 / 9780674660182"]], "The last of the Tsars : Nicholas II and the Russian revolution": [["Robert Service", "London : Macmillan, 2017.", "1447293096 / 9781447293095"]], "The Extreme Right in the French Resistance : members of the Cagoule and Corvignolles in the Second World War": [["Valerie Deacon", "Baton Rouge : Louisiana State University Press, [2016?].", "0807163627 / 9780807163627"]], "Cinema of paradox : French filmmaking under the German occupation": [["Evelyn Ehrlich", "New York : Columbia University Press, 1985", "0231059264 / 9780231059268"]], "Empire in the hills : Simla, Darjeeling, Ootacamund, and Mount Abu, 1820-1920": [["Queeny Pradhan", "New Delhi : Oxford University Press, 2017.", "0199463557 / 9780199463558"]], "Abandoning America : life-stories from early New England": [["Susan Hardman Moore", "Woodbridge : The Boydell Press, 2013.", "1843838176 / 9781843838173"]], "Anglo-Irish relations in the early Troubles : 1969-1972": [["Daniel C. Williamson", "London : Bloomsbury Academic, an imprint of Bloomsbury Publishing Plc, 2017.", "147421696X / 9781474216968"]], "The struggle for the South Atlantic : the Armada of the Strait, 1581-1584": [["Carla Rahn Phillips", "Abingdon, Oxon : Published by Routledge for the Hakluyt Society, London, 2016.", "1908145153 / 9781908145154"]], "Women's antiwar diplomacy during the Vietnam War era": [["Jessica M. Frazier", "Chapel Hill : The University of North Carolina Press, [2017]", "1469631784 / 9781469631783"]], "The Bamana empire by the Niger : kingdom, jihad, and colonization 1712-1920": [["Sundiata A. Djata", "Princeton : Markus Wiener, [1997?]", "1558761322 / 9781558761322"]], "Recollections : the French Revolution of 1848 and its aftermath": [["Alexis de Tocqueville", "Charlottesville : University of Virginia Press, 2016.", "0813939011 / 9780813939018"]], "Creating religious childhoods in Anglo-world and British colonial contexts, 1800-1950": [["Hugh Douglas Morrison", "London : Routledge, 2016.", "1472489489 / 9781472489487"]], "The art of the bribe : corruption under Stalin, 1943-1953": [["James W. Heinzen", "Stanford, California : New Haven : Hoover Institution, Stanford University ; Yale University Press, [2016]", "0300175256 / 9780300175257"]], "An ABC of Queen Victoria's empire : or a primer of conquest, dissent and disruption": [["Antoinette M. Burton", "London : Bloomsbury Academic, 2017.", "1474230156 / 9781474230155"]], "International order in diversity : war, trade and rule in the Indian Ocean": [["Andrew Phillips", "Cambridge : Cambridge University Press, 2015.", "1107084830 / 9781107084834"]], "Medieval women and their objects": [["Jenny Adams", "Ann Arbor : University of Michigan Press, [2017].", "0472130145 / 9780472130146"]]}